fw_meta/__init__.py
fw_meta/aliases.py
fw_meta/exports.py
fw_meta/imports.py
fw_meta/py.typed
fw_meta/utils.py
fw_meta-4.9.5.dist-info/METADATA
fw_meta-4.9.5.dist-info/WHEEL
fw_meta-4.9.5.dist-info/licenses/LICENSE
fw_meta-4.9.5.dist-info/RECORD
