Metadata-Version: 2.4
Name: fw-meta
Version: 4.9.5
Summary: Flywheel metadata extraction.
Project-URL: Repository, https://gitlab.com/flywheel-io/tools/lib/fw-meta
Project-URL: Documentation, https://gitlab.com/flywheel-io/tools/lib/fw-meta
Author-email: Flywheel <support@flywheel.io>
License-Expression: MIT
License-File: LICENSE
Keywords: DICOM,Flywheel,extract,metadata
Classifier: Topic :: Scientific/Engineering :: Medical Science Apps.
Classifier: Topic :: Software Development :: Libraries :: Python Modules
Requires-Python: <4,>=3.10
Requires-Dist: fw-utils>=4.2.5
Requires-Dist: pydantic>=2.1.1
